Workbook

Sheet Synthèse
A1: Cadrage Sprint 1 : plateforme de feedbacks internes
A3: Sprint goal | B3: À la fin du sprint 1, un collaborateur ou un manager peut lancer une évaluation, recueillir les feedbacks de ses collègues, suivre leur avancement, puis consulter les résultats dans son historique.
A4: Périmètre | B4: Cycle demander, répondre, suivre, consulter, pour deux rôles (Manager et Utilisateur). Admin, notifications externes (e-mail, Slack, Teams), anonymat : plus tard.
A5: Règle de décision | B5: Chaque coupe se justifie par la valeur, le risque ou une dépendance. En cas d'imprévu, on ne coupe jamais un Must : on retire d'abord un Should.
A6: Definition of Ready | B6: Une story est prête quand l'équipe peut la prendre en sprint sans poser de question : besoin clair, critères d'acceptation écrits, estimation faite, aucun blocage.
A7: Definition of Done | B7: Une story est terminée quand ses critères d'acceptation sont validés et qu'un utilisateur peut réellement faire le parcours de bout en bout.
A8: Suivi | B8: Tableau de sprint (À faire, En cours, En recette, Terminé), daily de 15 min, revue de mi-sprint au jour 5. Indicateur suivi en priorité : la chaîne critique (8 étapes), pas le nombre de stories terminées.
A9: En cas d'imprévu | B9: 1) Mesurer l'écart en jours et son effet sur la chaîne critique. 2) Ne jamais couper un Must. Couper d'abord un Should (ordre : US-17, US-13, US-15, US-16, US-14, US-12). 3) Si cela ne suffit pas, prévenir la direction le jour même et arbitrer avec elle entre périmètre et date. 4) Garder l'objectif du sprint : le cycle complet, du lancement aux résultats.
A10: Should | B10: Candidats, à engager selon la capacité réelle constatée au jour 5. Seuls les Must sont un engagement.
A12: Capacité (estimation relative, à calibrer avec le Tech Lead)
A13: Hypothèse (modifiable) | B13: Classique | C13: Assisté par IA
A14: Développeurs | B14: 4 | C14: 4
A15: Jours ouvrés du sprint | B15: 10 | C15: 10
A16: Jours-dev pour une story S | B16: 1.5 | C16: =B16/2 -> 0.75
A17: Jours-dev pour une story M | B17: 3.5 | C17: =B17/2 -> 1.75
A19: Calcul | B19: Classique | C19: Assisté par IA
A20: Capacité brute (jours-dev) | B20: =B14*B15 -> 40 | C20: =C14*C15 -> 40
A21: Must : nombre de S | B21: =COUNTIFS(Backlog!$D$2:$D$21,"Must",Backlog!$E$2:$E$21,"S") -> 8 | C21: =COUNTIFS(Backlog!$D$2:$D$21,"Must",Backlog!$E$2:$E$21,"S") -> 8
A22: Must : nombre de M | B22: =COUNTIFS(Backlog!$D$2:$D$21,"Must",Backlog!$E$2:$E$21,"M") -> 4 | C22: =COUNTIFS(Backlog!$D$2:$D$21,"Must",Backlog!$E$2:$E$21,"M") -> 4
A23: Must (jours-dev) | B23: =B21*B16+B22*B17 -> 26 | C23: =C21*C16+C22*C17 -> 13
A24: Must (% de la capacité brute) | B24: =B23/B20 -> 0.65 | C24: =C23/C20 -> 0.325
A25: Should : nombre de S | B25: =COUNTIFS(Backlog!$D$2:$D$21,"Should",Backlog!$E$2:$E$21,"S") -> 4 | C25: =COUNTIFS(Backlog!$D$2:$D$21,"Should",Backlog!$E$2:$E$21,"S") -> 4
A26: Should : nombre de M | B26: =COUNTIFS(Backlog!$D$2:$D$21,"Should",Backlog!$E$2:$E$21,"M") -> 2 | C26: =COUNTIFS(Backlog!$D$2:$D$21,"Should",Backlog!$E$2:$E$21,"M") -> 2
A27: Should (jours-dev) | B27: =B25*B16+B26*B17 -> 13 | C27: =C25*C16+C26*C17 -> 6.5
A28: Must + Should (% de la capacité brute) | B28: =(B23+B27)/B20 -> 0.975 | C28: =(C23+C27)/C20 -> 0.4875
A30: Marge (cérémonies, bugs, recette) | B30: 0.15 | C30: 0.15
A31: Capacité nette (jours-dev) | B31: =B20*(1-B30) -> 34 | C31: =C20*(1-C30) -> 34
A32: Must (% de la capacité nette) | B32: =B23/B31 -> 0.76470588 | C32: =C23/C31 -> 0.38235294
A33: Must + Should (% de la capacité nette) | B33: =(B23+B27)/B31 -> 1.1470588 | C33: =(C23+C27)/C31 -> 0.57352941
A35: Les conversions S/M en jours sont des ordres de grandeur, pas des données : aucun document ne donne la vélocité de l'équipe. Cellules jaunes = hypothèses modifiables.

Sheet Backlog
A1: ID | B1: Story | C1: Rôle | D1: Priorité | E1: Taille | F1: Dépend de | G1: Pourquoi
A2: EN-01 | B2: Comptes de démo et sélecteur de profil (enabler) | C2: Équipe | D2: Must | E2: S | F2: n/a | G2: Sans utilisateurs ni managers, rien ne tourne
A3: US-01 | B3: Sélectionner le formulaire standard | C3: Utilisateur et Manager | D3: Must | E3: S | F3: n/a | G3: Un seul formulaire au sprint 1 : sans formulaire, pas d'évaluation
A4: US-02 | B4: Créer une évaluation pour moi | C4: Utilisateur | D4: Must | E4: M | F4: EN-01, US-01 | G4: Cœur du parcours Utilisateur
A5: US-03 | B5: Créer une évaluation pour un membre de mon équipe | C5: Manager | D5: Must | E5: M | F5: US-02 | G5: Cœur du rôle Manager
A6: US-04 | B6: Lancer une évaluation (dès 1 personne) | C6: Utilisateur et Manager | D6: Must | E6: S | F6: US-02 | G6: Sans lancement, pas de collecte
A7: US-05 | B7: Ajouter une personne après lancement | C7: Utilisateur et Manager | D7: Must | E7: S | F7: US-04 | G7: Demandé dans le cahier des charges
A8: US-06 | B8: Retirer une personne d'une évaluation en cours | C8: Utilisateur et Manager | D8: Must | E8: S | F8: US-05 | G8: Symétrique de l'ajout : corrige une erreur de ciblage sans attendre la clôture
A9: US-07 | B9: Voir mes feedbacks à compléter (avec compteur) | C9: Utilisateur | D9: Must | E9: S | F9: US-04 | G9: Sans cette liste, personne ne répond. Le compteur remplace les notifications
A10: US-08 | B10: Répondre : brouillon, envoi | C10: Utilisateur | D10: Must | E10: M | F10: US-07 | G10: Cœur de la valeur
A11: US-09 | B11: Suivre l'avancement | C11: Utilisateur et Manager | D11: Must | E11: S | F11: US-08 | G11: Un des trois enjeux du produit. Porte aussi la vue Manager de l'équipe
A12: US-10 | B12: Clôturer une évaluation | C12: Utilisateur et Manager | D12: Must | E12: M | F12: US-09 | G12: Sans clôture, pas de résultats ni d'historique
... A19: US-17 | B19: Archiver une évaluation | C19: Utilisateur et Manager | D19: Should | E19: S | F19: US-10 | G19: Peut attendre
A20: US-18 | B20: Proposer des personnes à interroger | C20: Utilisateur | D20: Sprint 2 | F20: US-04 | G20: Flux à deux acteurs (proposition puis validation) pour un gain faible
A21: US-19 | B21: Dashboard manager | C21: Manager | D21: Sprint 2 | F21: US-09 | G21: La vue d'avancement de US-09 couvre le besoin minimal
A23: Légende des tailles (sert au calcul de capacité, voir Synthèse)
A24: Taille | B24: Définition | C24: Jours-dev | D24: Avec IA (÷ 2)
A25: S | B25: Un écran ou une règle simple, peu de cas limites | C25: =Synthèse!B16 -> 1.5 | D25: =Synthèse!C16 -> 0.75
A26: M | B26: Plusieurs écrans ou règles, avec des cas limites et des données liées | C26: =Synthèse!B17 -> 3.5 | D26: =Synthèse!C17 -> 1.75
A27: L | B27: Un parcours complet ou un sujet technique lourd. Aucune story L dans ce backlog : on la redécoupe avant le sprint | C27: 6 | D27: =C28/2 -> 0
A28: Ordres de grandeur, à calibrer avec le Tech Lead. Les jours-dev se modifient dans les cellules jaunes de la Synthèse.

Sheet Dépendances
A1: Dépendances entre les stories du sprint 1 (Must)
A30: Lecture | B30: Une flèche signifie « ne peut commencer que quand la précédente est finie ». Rose : chaîne critique, 8 étapes enchaînées. Gris : hors chaîne, peut glisser sans bloquer l'objectif.
A31: À retenir | B31: 8 étapes enchaînées pour un sprint de 10 jours : si chaque story attend la précédente, le sprint ne tient pas. On développe donc en parallèle sur des données simulées, le prototype servant de spécification, et on surveille cette chaîne en priorité.

Sheet User stories
A1: ID | B1: Priorité | C1: Story | D1: Critères d'acceptation (Soit / Quand / Alors)
A2: EN-01 | B2: Must | C2: Équipe : je veux des utilisateurs de démonstration avec leur manager et un sélecteur de profil, afin de tester tous les parcours sans authentification. | D2: Soit des managers et des collaborateurs de démonstration, quand je change de profil, alors je ne vois que mes données. Soit un manager, alors il a les onglets utilisateur et « Mon équipe ».
A3: US-01 | B3: Must | C3: Je veux sélectionner le formulaire standard « Feedback standard » pour mon évaluation, afin de poser les bonnes questions sans avoir à le construire. | D3: Soit le formulaire standard, alors il contient une note de 1 à 5, un choix multiple et une question ouverte. Soit une évaluation en création, quand je choisis le formulaire, alors « Feedback standard » est proposé. Soit une évaluation sans formulaire, alors elle ne peut pas être lancée.
A4: US-02 | B4: Must | C4: En tant que collaborateur, je veux définir un nom, une période, une date limite, un formulaire et des personnes à interroger, afin de demander des retours sur mon travail. | D4: Soit une date limite passée ou du jour, quand je lance, alors un message d'erreur apparaît et rien n'est lancé. Soit moi-même dans les personnes interrogées, alors c'est refusé. Soit un brouillon, quand je l'enregistre, alors il reste en brouillon, visible de moi seul.
A5: US-03 | B5: Must | C5: En tant que manager, je veux créer une évaluation pour un collaborateur de mon équipe et choisir les personnes interrogées, afin de piloter la dynamique d'équipe. | D5: Soit un membre de mon équipe, quand je lance l'évaluation, alors elle apparaît dans son espace. Soit un collaborateur d'une autre équipe, alors je ne peux pas le choisir. Soit moi-même, alors l'auto-évaluation est possible.
A6: US-04 | B6: Must | C6: Je veux lancer mon évaluation, afin que les personnes interrogées reçoivent leur demande. | D6: Soit 0 personne interrogée, alors le bouton Lancer est inactif et l'évaluation reste en brouillon. Soit 1 personne ou plus et des champs valides, quand je lance, alors l'évaluation passe « En cours » et chaque personne reçoit une demande « Envoyé ». Soit une personne déjà choisie, alors elle ne peut pas l'être deux fois.
A7: US-05 | B7: Must | C7: Je veux ajouter une personne à une évaluation en cours, afin d'obtenir un avis oublié sans tout recréer. | D7: Soit une évaluation en cours, quand j'ajoute une personne, alors elle reçoit une demande « Envoyé » et le compteur passe de 1/1 à 1/2. Soit une personne déjà interrogée ou la personne évaluée, alors l'ajout est refusé. Soit une évaluation clôturée, alors l'ajout est impossible.
A8: US-06 | B8: Must | C8: Je veux retirer une personne d'une évaluation en cours, afin de corriger une erreur de ciblage sans attendre la clôture. | D8: Soit une demande « Envoyé » ou « Brouillon », quand je retire la personne, alors sa demande est supprimée et le compteur se met à jour. Pour un brouillon de réponse, la confirmation prévient qu'il sera perdu. Soit une demande « Terminé », alors le retrait est impossible : le feedback est conservé. Soit une seule personne interrogée, alors le retrait est impossible : il faut clôturer. Soit une personne retirée, quand je l'ajoute de nouveau, alors elle reçoit une nouvelle demande.
A9: US-07 | B9: Must | C9: Je veux voir la liste des demandes qu'on m'adresse, afin de savoir lesquelles traiter. | D9: Soit des demandes reçues, alors je vois l'évaluation, la personne évaluée, la date limite et le statut. Soit des demandes « Envoyé » ou « Brouillon » sur des évaluations en cours, alors l'onglet Feedback affiche leur nombre. Soit une date limite dépassée, alors la demande est signalée en retard et la réponse reste possible jusqu'à la clôture.
A10: US-08 | B10: Must | C10: Je veux répondre à une demande, en brouillon puis en envoi, afin de donner un retour juste, à mon rythme. | D10: Soit une réponse en cours, quand je l'enregistre en brouillon, alors je peux la reprendre plus tard. Soit une question obligatoire vide, quand j'envoie, alors l'envoi est bloqué avec un message clair. Soit un envoi réussi, alors la demande passe « Terminé » et n'est plus modifiable. Soit une évaluation clôturée, alors je ne peux plus répondre.
A11: US-09 | B11: Must | C11: Je veux voir où en est chaque personne interrogée, afin de savoir qui n'a pas encore répondu, sans interroger tout le monde. | D11: Soit une évaluation en cours, alors je vois le statut de chaque personne et un compteur du type « 3/5 terminés ». Soit une évaluation en cours, alors le contenu des réponses reste masqué. Soit un autre collaborateur que le créateur, la personne évaluée ou son manager, alors je n'ai pas accès à cet avancement. Soit un manager, quand j'ouvre « Mon équipe », alors je vois les évaluations en cours des membres de mon équipe et leur avancement.
A12: US-10 | B12: Must | C12: Je veux clôturer une évaluation, afin de figer la période et d'ouvrir les résultats. | D12: Soit une évaluation en cours, quand je clique sur Clôturer, alors une confirmation indique combien de demandes ne sont pas terminées. Soit la clôture confirmée, alors les demandes « Envoyé » et « Brouillon » passent « Expiré » et l'évaluation est figée, sans réouverture possible. Soit une évaluation clôturée, alors ses résultats deviennent visibles.
... A21: US-19 | B21: Sprint 2 | C21: En tant que manager, je veux un tableau de bord de mon équipe, afin de repérer d'un coup d'œil les retards. | D21: À détailler en affinage avant le sprint 2.
A23: EN-01 est un enabler (tâche technique), pas une user story. Les stories du sprint 2 ne sont volontairement pas détaillées : on affine seulement ce qui entre dans le prochain sprint. Les Should sont des candidats, engagés selon la capacité.

Sheet Angles morts
A1: Sujet | B1: Risque | C1: Hypothèse sprint 1 | D1: Question à poser
A2: Confidentialité et anonymat | B2: Feedbacks moins sincères, ou modèle de données à refaire si l'anonymat arrive plus tard | C2: Auteur nommé. Contenu visible à la personne évaluée et à son manager après clôture | D2: L'auteur d'un feedback est-il nommé ou anonyme ? Dans quels cas ?
A3: Cadre RH et juridique | B3: Blocage au déploiement (information des salariés, CSE, RGPD) | C3: Hors sprint, à traiter avant toute mise en production | D3: Qui valide côté RH et juridique ? Quelle durée de conservation ?
A4: Canal de notification | B4: Dépendance externe (app Slack ou Teams à faire approuver) | C4: Pas de notification externe en sprint 1. Compteur de demandes en attente sur l'onglet Feedback | D4: Quel canal : e-mail, Slack, Teams ? Le cahier des charges ne mentionne pas Teams, à ma lecture
A5: Clôture définitive | B5: Erreur de clôture irréversible | C5: Confirmation indiquant le nombre de demandes non terminées. Pas de réouverture | D5: Faut-il prévoir une réouverture par un admin en sprint 2 ?
A6: Choix libre des personnes | B6: Fatigue et spam si chacun peut interroger tout le monde | C6: Choix parmi tous les collaborateurs, sans plafond | D6: Faut-il plafonner le nombre de demandes par personne et par période ?
A7: Changement de manager ou compte désactivé | B7: Droits d'accès et feedbacks en attente orphelins | C7: Hors sprint 1 (Admin) | D7: Qui garde l'accès à l'historique quand un manager change ?
A8: Vocabulaire | B8: Mots différents selon les interlocuteurs | C8: « Évaluation » dans le prototype | D8: « Évaluation » ou « Demande de feedback » ? Le brief parle aussi d'états Envoyé, En cours, Terminé
A9: Capacité de l'équipe | B9: Sprint sur- ou sous-dimensionné | C9: 4 développeurs, 2 semaines, avec ou sans IA | D9: Effectif, durée de sprint et vélocité réelles ? (Tech Lead)
A10: Chaîne de dépendances | B10: 8 étapes enchaînées pour 10 jours de sprint | C10: Développement en parallèle sur données simulées, prototype comme spécification | D10: L'équipe peut-elle travailler en parallèle sur une spécification partagée ? (Tech Lead)
A11: Démo | B11: Plantage pendant l'atelier | C11: Plan B : capture vidéo du parcours et lien déployé

Sheet Hypothèses
A1: Hypothèse prise | B1: Si elle est fausse | C1: À valider avec
A2: 4 développeurs, sprint de 2 semaines | B2: Le sprint est sur- ou sous-dimensionné : on ajuste les Should | C2: Tech Lead
A3: Les développeurs travaillent avec l'IA | B3: La capacité passe du scénario assisté au scénario classique (voir Synthèse) | C3: Tech Lead
A4: Auteur des feedbacks nommé | B4: Le modèle de données et les règles de visibilité sont à revoir | C4: Direction
A5: Résultats visibles à la clôture seulement | B5: On ajoute un affichage progressif et le risque de biais | C5: Direction, Expert métier
A6: Clôture définitive, sans réouverture | B6: On ajoute une réouverture (mémorisation des demandes expirées) | C6: Direction
A7: Lancement dès 1 personne interrogée | B7: On impose un minimum de personnes | C7: Expert métier
A8: Choix libre parmi tous les collaborateurs, sans plafond | B8: Il faut un plafond de demandes par personne | C8: Direction, RH
A9: Pas de notification externe (e-mail, Slack, Teams) en sprint 1, un compteur dans l'onglet Feedback | B9: Le taux de réponse peut chuter : les notifications passent en Must | C9: Direction
A10: Socle technique (dépôt, base de données, environnement de recette) fourni par l'équipe | B10: Un enabler de mise en place est à ajouter et à chiffrer au sprint 1 | C10: Tech Lead
A11: Environ 150 utilisateurs | B11: Volumes et performances à revoir | C11: Direction
A12: Formulaire figé à la création (prototype) | B12: Règle cible : modifiable tant qu'il y a 0 réponse (US-14, Should) | C12: Direction, Tech Lead

Sheet Ouvertures
A1: Thème | B1: Sprint 2 et au-delà
A2: Anonymat | B2: Évaluations anonymes (360°, feedback montant), avec un seuil minimum de répondants
A3: Notifications | B3: Slack, Teams ou e-mail, rappels automatiques
A4: Admin | B4: Import CSV, changement de manager avec historique, statistiques agrégées sans accès au contenu
A5: Manager | B5: Tableau de bord d'équipe (US-19), propositions de personnes par les utilisateurs (US-18), relance manuelle d'un retardataire
A6: Visibilité et profils | B6: Visibilité des résultats paramétrable par l'Admin, profils métier (RH, direction), statistiques agrégées
A7: Autres | B7: Export PDF pour l'entretien annuel, feedback spontané, campagnes en masse, pipeline CI/CD en enabler
